{
  "parent": "minecraft:recipes/root",
  "rewards": {
    "recipes": [
      "dragonmounts:enchant_dragon_shovel"
    ]
  },
  "criteria": {
    "has_dragon_scales": {
      "trigger": "minecraft:inventory_changed",
      "conditions": {
        "items": [
          {
            "item": "dragonmounts:enchant_dragon_scales"
          }
        ]
      }
    },
    "has_the_recipe": {
      "trigger": "minecraft:recipe_unlocked",
      "conditions": {
        "recipe": "dragonmounts:enchant_dragon_shovel"
      }
    }
  },
  "requirements": [
    [
      "has_dragon_scales",
      "has_the_recipe"
    ]
  ]
}